Andreani_QA_Sikuli/Sikuli.py
Andreani_QA_Sikuli/__init__.py
Andreani_QA_Sikuli-0.0.4.dist-info/METADATA
Andreani_QA_Sikuli-0.0.4.dist-info/WHEEL
Andreani_QA_Sikuli-0.0.4.dist-info/top_level.txt
Andreani_QA_Sikuli-0.0.4.dist-info/RECORD
